mimic_hand_api/.gitignore
mimic_hand_api/RP2040/__init__.py
mimic_hand_api/RP2040/mimic_hand.proto
mimic_hand_api/RP2040/mimic_hand_pb2.py
mimic_hand_api/RP2040/rp2040_client.py
mimic_hand_api/__init__.py
mimic_hand_api/motor_map.yaml
mimic_hand_api/rp2040_api.py
mimic_hand_api-4.2.0.dist-info/METADATA
mimic_hand_api-4.2.0.dist-info/WHEEL
mimic_hand_api-4.2.0.dist-info/RECORD
