Metadata-Version: 2.1
Name: mimic_hand_api
Version: 4.2.0
Summary: API for the low-level control the motors in our hands (P4).
License: Closed source
Author: Ben Forrai
Author-email: ben.forrai@mimicrobotics.com
Requires-Python: ==3.10.12
Classifier: License :: Other/Proprietary License
Classifier: Programming Language :: Python :: 3
Requires-Dist: numpy (>=1.26.4,<2.0.0)
Requires-Dist: protobuf (>=5.28.3,<6.0.0)
Requires-Dist: pyserial (>=3.5,<4.0)
Requires-Dist: pyyaml (>=6.0.0,<7.0.0)
